onemillion/__init__.py
onemillion/__main__.py
onemillion/cli.py
onemillion/onemillion.py
onemillion-0.4.1.dist-info/DESCRIPTION.rst
onemillion-0.4.1.dist-info/METADATA
onemillion-0.4.1.dist-info/RECORD
onemillion-0.4.1.dist-info/WHEEL
onemillion-0.4.1.dist-info/metadata.json
onemillion-0.4.1.dist-info/top_level.txt
