Metadata-Version: 2.0
Name: onemillion
Version: 0.4.1
Summary: Determine if a domain is in the Alexa or Cisco top one million domain list.
Home-page: https://github.com/fhightower/onemillion
Author: Floyd Hightower
Author-email: UNKNOWN
License: MIT license
Keywords: onemillion
Platform: UNKNOWN
Classifier: Development Status :: 2 - Pre-Alpha
Classifier: Intended Audience :: Developers
Classifier: License :: OSI Approved :: MIT License
Classifier: Natural Language :: English
Classifier: Programming Language :: Python :: 2
Classifier: Programming Language :: Python :: 2.6
Classifier: Programming Language :: Python :: 2.7
Classifier: Programming Language :: Python :: 3
Classifier: Programming Language :: Python :: 3.3
Classifier: Programming Language :: Python :: 3.4
Classifier: Programming Language :: Python :: 3.5
Requires-Dist: Requests
